<Glyph name="greater_greater_equal.liga" lsb="-1154" width="625">
    <CharString>
        {3f81bb4e} callsubr
        -1154 1692 hintmask 10010000
        -718 277 rmoveto
        103 vlineto
        -364 300 {07c30815} callsubr
        hintmask 00110000
        1626 431 rmoveto
        104 -991 vlineto
        {e0f54d80} callsubr
        978 104 -852 {03d3c78d} callsubr
        endchar
    </CharString>
    <Subrs>
        <CharString index="0" fingerprint="3f81bb4e">
            -27 707 -520 {9791c2d3} callsubr
            return
        </CharString>
        <CharString index="1" fingerprint="9791c2d3">
            {d8acdd14} callgsubr
            hstemhm
            return
        </CharString>
        <CharString index="2" fingerprint="07c30815">
            -69 -88 322 -258 rlineto
            -12 vlineto
            -325 -262 66 -87 rlineto
            return
        </CharString>
        <CharString index="3" fingerprint="e0f54d80">
            hintmask 10010000
            -209 172 {07c30815} callsubr
            hintmask 01010000
            228 187 rlineto
            return
        </CharString>
        <CharString index="4" fingerprint="03d3c78d">
            hlineto
            16 13 rlineto
            103 vlineto
            hintmask 00110000
            -29 24 rlineto
            return
        </CharString>
    </Subrs>
    <GlobalSubrs>
        <CharString index="0" fingerprint="d8acdd14">
            104 140 104 return
        </CharString>
    </GlobalSubrs>
</Glyph>