<Glyph name="less_hyphen_hyphen.liga" lsb="-1153" width="625">r
    <CharString>r
        {77357d67} callgsubr
        -1153 1650 hintmask 01100000
        {e8b0cb7f} callgsubr
        -1472 hlineto
        305 201 rlineto
        hintmask 10100000
        {0bf7e66c} callgsubr
        rlineto
        hintmask 01100000
        -222 221 rlineto
        endcharr
    </CharString>r
    <Subrs/>r
    <GlobalSubrs>r
        <CharString index="0" fingerprint="77357d67">r
            -24 703 -401 105 hstemhm
            returnr
        </CharString>r
        <CharString index="1" fingerprint="e8b0cb7f">r
            477 278 rmoveto
            20 105 rlineto
            returnr
        </CharString>r
        <CharString index="2" fingerprint="0bf7e66c">r
            -51 95 -414 -278 -18 -102 311 -323 83 81 returnr
        </CharString>r
    </GlobalSubrs>r
</Glyph>
