<Subrs>
    
          
    <!-- The 'index' attribute is only for humans; it is ignored when parsed. -->
    
          
    <CharString index="0">
        
            rmoveto
            47 -48 43 -47 39 vhcurveto
            40 22 50 25 63 30 -19 34 rcurveline
            -67 -32 -55 -28 -45 -24 rrcurveto
            -35 30 -29 28 27 vvcurveto
            38 46 32 138 -32 vhcurveto
            19 56 37 callsubr
            28 -88 -61 -66 vvcurveto
            -38 33 -35 39 -34 vhcurveto
            -112 -66 -24 -39 -42 vvcurveto
            -58 58 -40 85 98 70 52 64 vhcurveto
            -157 -69 rmoveto
            -55 -42 24 41 25 17 27 93 55 hvcurveto
            46 -38 43 -35 -34 vvcurveto
            -36 -41 -29 -61 vhcurveto
            endchar
          
    </CharString>
    
          
    <CharString index="1">
        
            rmoveto
            -11 39 rlineto
            -246 -92 -116 42 151 vvcurveto
            5 vlineto
            257 19 146 77 125 vvcurveto
            77 -57 49 -93 -185 -136 -191 -170 -182 156 -95 285 146 38 callgsubr
            432 rmoveto
            61 37 -31 -47 -97 -132 -54 -199 -15 hvcurveto
            121 18 87 123 128 hhcurveto
            endchar
          
    </CharString>
    
          
    <CharString index="2">
        
            rmoveto
            170 -78 87 -115 -186 -133 -230 -229 -170 78 -87 115 186 133 230 229 vhcurveto
            -438 37 callgsubr
            193 97 197 137 79 51 -65 -133 -193 -97 -197 -137 -79 -51 65 133 vhcurveto
            endchar
          
    </CharString>
    
          
    <CharString index="3">
        
            -101 callsubr
            -7 -54 rlineto
            241 -19 85 80 76 vvcurveto
            return
          
    </CharString>
    
          
    <CharString index="4">
        
            rmoveto
            -41 27 rlineto
            -81 -64 -50 -46 -59 hhcurveto
            -56 -36 37 94 -39 hvcurveto
            -55 -27 rlineto
            -111 42 56 -51 73 hhcurveto
            77 76 58 100 76 hvcurveto
            return
          
    </CharString>
    
          
    <CharString index="5">
        
            269 193 104 173 129 vvcurveto
            70 -37 41 -63 -151 -193 -294 -300 vhcurveto
            -6 vlineto
            -23 -16 -34 -23 -14 -8 21 -34 rcurveline
            53 34 22 -172 132 -15 204 123 rlinecurve
            -40 641 rmoveto
            34 22 -24 -45 -97 -80 -146 -226 -173 hvcurveto
            251 9 141 234 100 hhcurveto
            return
          
    </CharString>
    
          
    <CharString index="6">
        
            rmoveto
            54 -50 51 -157 27 vhcurveto
            29 119 17 callgsubr
            hlineto
            15 50 rlineto
            -261 hlineto
            -51 -206 rlineto
            162 -24 51 -37 -41 vvcurveto
            -46 -59 -48 -203 18 vhcurveto
            return
          
    </CharString>
    
          
    <CharString index="7">
        
            16 63 rlineto
            -333 hlineto
            50 258 25 callgsubr
            hlineto
            11 55 rlineto
            -281 hlineto
            48 250 rlineto
            331 hlineto
            13 62 rlineto
            -404 -50 callgsubr
            return
          
    </CharString>
    
          
    <CharString index="8">
        
            322 hlineto
            12 50 rlineto
            -128 hlineto
            81 408 -58 -5 -13 -68 -143 -18 -7 -44 139 10 -55 -283 rlineto
            -140 hlineto
            return
          
    </CharString>
    
          
    <CharString index="9">
        
            rmoveto
            56 hlineto
            15 49 rlineto
            -61 hlineto
            30 154 -55 -5 -29 -149 rlineto
            -176 hlineto
            58 83 43 78 45 136 -62 3 rcurveline
            -42 -132 -40 -80 -60 -98 -4 -39 rcurveline
            228 hlineto
            return
          
    </CharString>
    
          
    <CharString index="10">
        
            310 hlineto
            11 51 rlineto
            -234 hlineto
            171 107 97 75 94 vvcurveto
            89 -89 46 -180 -27 vhcurveto
            -8 -53 42 callgsubr
            23 56 -33 -58 vvcurveto
            -79 -109 -74 -185 -114 vhcurveto
            return
          
    </CharString>
    
          
    <CharString index="11">
        
            rmoveto
            29 -379 rlineto
            81 hlineto
            43 130 76 262 71 296 rrcurveto
            -70 hlineto
            -41 -174 -85 -337 -26 -86 rrcurveto
            -4 hlineto
            -29 395 rlineto
            -47 hlineto
            -182 -395 rlineto
            -4 hlineto
            7 86 45 337 27 174 rrcurveto
            -71 hlineto
            -44 -295 -27 -263 -6 -130 rrcurveto
            81 hlineto
            endchar
          
    </CharString>
    
          
    <CharString index="12">
        
            rmoveto
            20 30 -60 50 -84 89 -50 65 rlinecurve
            -53 -56 60 -61 101 -77 66 -40 rlinecurve
            return
          
    </CharString>
    
          
    <CharString index="13">
        
            rmoveto
            13 -50 rlineto
            227 62 77 128 116 vvcurveto
            105 -69 50 -85 -95 -74 -62 -92 -118 141 -45 117 92 vhcurveto
            -22 -71 -67 -75 -163 -40 rrcurveto
            48 265 rmoveto
            56 40 43 66 56 51 -32 -85 -8 0 -8 -1 -8 vhcurveto
            -103 -81 -109 36 87 vvcurveto
            endchar
          
    </CharString>
    
          
    <CharString index="14">
        
            rmoveto
            hintmask 00111100
            -78 callsubr
            hintmask 01011100
            -92 callgsubr
            hintmask 10011100
            -100 callgsubr
          
    </CharString>
    
          
    <CharString index="15">
        
            rmoveto
            3 hlineto
            223 163 -34 38 -178 -129 -115 134 return
          
    </CharString>
    
          
    <CharString index="16">
        
            -79 callgsubr
            -180 -490 -107 callsubr
          
    </CharString>
    
          
    <CharString index="17">
        
            rmoveto
            50 -310 rlineto
            65 hlineto
            68 189 53 167 49 182 rrcurveto
            -74 hlineto
            -37 -157 -37 -139 -42 -149 rrcurveto
            -5 hlineto
            -47 313 rlineto
            -46 hlineto
            -166 -312 rlineto
            -3 hlineto
            15 146 16 140 22 158 rrcurveto
            -70 hlineto
            -27 -200 -16 -203 -5 -135 rrcurveto
            70 hlineto
            endchar
          
    </CharString>
    
          
    <CharString index="18">
        
            -39 callsubr
            76 73 34 80 72 vvcurveto
            -93 -3 13 -63 -3 -66 -55 -78 rlinecurve
            endchar
          
    </CharString>
    
          
    <CharString index="19">
        
            -98 callsubr
            -18 -94 rlineto
            54 hlineto
            endchar
          
    </CharString>
    
          
    <CharString index="20">
        
            -81 callsubr
            endchar
          
    </CharString>
    
          
    <CharString index="21">
        
            -271 -148 rmoveto
            72 1 43 146 -79 -2 rlineto
            return
          
    </CharString>
    
          
    <CharString index="22">
        
            rmoveto
            66 2 90 389 -69 -3 -43 -193 rlineto
            -176 -61 -97 64 181 vvcurveto
            186 107 196 142 83 14 -66 -120 -3 vhcurveto
            68 hlineto
            170 7 -40 81 -118 hhcurveto
            -181 -151 -221 -239 hvcurveto
            return
          
    </CharString>
    
          
    <CharString index="23">
        
            rmoveto
            168 -579 42 callsubr
            hintmask 01010100
            134 688 rlineto
            -68 hlineto
            hintmask 10010100
            -108 -566 rlineto
            -6 hlineto
            hintmask 01001100
            -160 568 rlineto
            hintmask 01010100
            -83 -3 -133 -687 rlineto
            68 hlineto
            hintmask 01100100
            110 579 rlineto
            return
          
    </CharString>
    
          
    <CharString index="24">
        
            -135 -98 -96 -103 hvcurveto
            -161 289 -71 -121 vvcurveto
            -74 -95 -59 -290 73 vhcurveto
            -16 -72 rlineto
            343 -74 131 103 111 154 -289 65 136 vvcurveto
            67 59 60 82 80 45 -41 -97 14 vhcurveto
            return
          
    </CharString>
    
          
    <CharString index="25">
        
            rmoveto
            -54 callsubr
            -48 -54 -67 -61 -13 2 -13 3 -13 hvcurveto
            -40 -47 -58 -47 -99 -72 19 -34 rcurveline
            84 53 65 49 48 45 rrcurveto
            46 -92 93 -78 -66 vvcurveto
            -55 -51 -40 -251 23 vhcurveto
            hintmask 01110000
            -3 -66 rlineto
            296 -19 78 79 84 vvcurveto
            endchar
          
    </CharString>
    
          
    <CharString index="26">
        
            rmoveto
            -97 callsubr
            return
          
    </CharString>
    
          
    <CharString index="27">
        
            rmoveto
            160 128 151 194 53 -11 44 -19 34 hvcurveto
            hintmask 01011100
            69 77 -42 32 -60 -67 rlineto
            hintmask 01101100
            30 -33 -45 16 -53 hhcurveto
            -161 -127 -155 -191 -55 11 -45 21 -34 hvcurveto
            -69 -77 42 -31 61 67 24 callgsubr
            -28 33 43 -15 52 hhcurveto
            -124 229 rmoveto
            149 84 127 121 41 33 -14 -27 24 vhcurveto
            -288 -325 rlineto
            -10 25 -5 30 35 vvcurveto
            137 -170 rmoveto
            -40 -32 13 25 -23 hvcurveto
            286 323 rlineto
            9 -24 5 -29 -33 vvcurveto
            -150 -85 -125 -120 vhcurveto
            endchar
          
    </CharString>
    
          
    <CharString index="28">
        
            198 -313 rlineto
            hintmask 00111000
            79 12 -188 290 rlineto
            141 68 80 71 102 vvcurveto
            109 -105 76 -277 -36 vhcurveto
            hintmask 01011000
            -132 -686 rlineto
            72 hlineto
            121 629 rlineto
            168 18 81 -43 -81 vvcurveto
            -82 -71 -58 -166 -73 vhcurveto
            endchar
          
    </CharString>
    
          
    <CharString index="29">
        
            72 6 -21 230 -25 229 -27 229 rlinecurve
            -103 hlineto
            return
          
    </CharString>
    
          
    <CharString index="30">
        
            rmoveto
            -9 38 -239 -88 -39 46 30 130 rlinecurve
            67 299 rlineto
            217 hlineto
            10 55 rlineto
            -214 hlineto
            35 157 -54 -3 -80 -154 rlineto
            -71 hlineto
            -15 -55 rlineto
            103 hlineto
            -68 -303 -40 -174 87 -88 280 140 rlinecurve
            return
          
    </CharString>
    
          
    <CharString index="31">
        
            -88 -78 -59 -44 -53 hhcurveto
            -52 -25 40 105 24 hvcurveto
            return
          
    </CharString>
    
          
    <CharString index="32">
        
            rmoveto
            31 56 rlineto
            -169 72 -73 48 54 vvcurveto
            hintmask 11010000
            76 132 40 81 vvcurveto
            37 -27 34 -75 22 vhcurveto
            hintmask 11101000
            102 24 41 52 44 55 -75 67 52 vvcurveto
            58 90 48 223 45 vhcurveto
            -12 62 rlineto
            -274 -65 -92 -80 -78 -69 75 -60 -47 vvcurveto
            -37 -41 -38 -148 -8 vhcurveto
            -10 -52 rlineto
            hintmask 11010000
            108 -11 47 -28 -39 -62 -134 -41 -96 vvcurveto
            -70 80 -57 201 -89 vhcurveto
            endchar
          
    </CharString>
    
          
    <CharString index="33">
        
            -68 callsubr
            hintmask 01101100
            56 -26 45 -68 -69 -82 -43 -84 -81 vhcurveto
            hintmask 01011100
            -78 callgsubr
            hintmask 01101100
            79 78 71 40 52 hhcurveto
            40 19 -24 -44 hvcurveto
            hintmask 10011100
            -38 callgsubr
          
    </CharString>
    
          
    <CharString index="34">
        
            -68 callsubr
            hintmask 01101110
            56 -26 45 -68 -69 -82 -43 -84 -81 vhcurveto
            hintmask 01011110
            -78 callgsubr
            hintmask 01101110
            79 78 71 40 52 hhcurveto
            40 19 -24 -44 hvcurveto
            hintmask 10011110
            -55 callsubr
            return
          
    </CharString>
    
          
    <CharString index="35">
        
            435 hlineto
            17 62 -361 -2 434 420 11 59 rlineto
            -422 hlineto
            -17 -62 347 2 -433 -419 rlineto
            endchar
          
    </CharString>
    
          
    <CharString index="36">
        
            -71 -4 -78 -135 44 -27 -42 -184 rlineto
            return
          
    </CharString>
    
          
    <CharString index="37">
        
            46 57 46 68 44 79 -61 22 rcurveline
            -35 -69 -36 -59 -36 -49 -46 75 -26 77 -6 82 rrcurveto
            63 66 38 72 54 vvcurveto
            34 -19 17 -29 -50 -65 -114 -114 -2 vhcurveto
            return
          
    </CharString>
    
          
    <CharString index="38">
        
            -67 callgsubr
            48 48 return
          
    </CharString>
    
          
    <CharString index="39">
        
            rmoveto
            -12 37 rlineto
            -85 -36 -16 8 33 67 77 194 109 vvcurveto
            return
          
    </CharString>
    
          
    <CharString index="40">
        
            rmoveto
            71 2 44 146 -80 -2 rlineto
            return
          
    </CharString>
    
          
    <CharString index="41">
        
            rmoveto
            -99 callsubr
            endchar
          
    </CharString>
    
          
    <CharString index="42">
        
            630 55 65 55 -24 -20 hstemhm
            88 456 hintmask 11010000
            396 685 rmoveto
            -52 -19 120 -75 hhcurveto
            -54 -53 -51 -94 -55 hvcurveto
            37 -22 rlineto
            66 41 36 46 33 52 20 -120 75 hhcurveto
            hintmask 10110000
            55 52 56 95 55 hvcurveto
            -38 21 rlineto
            -66 -41 -36 -51 -33 hhcurveto
            endchar
          
    </CharString>
    
          
    <CharString index="43">
        
            -60 callsubr
            hstemhm
            96 71 233 71 hintmask 01101100
            return
          
    </CharString>
    
          
    <CharString index="44">
        
            420 hlineto
            14 63 rlineto
            -348 hlineto
            120 625 -10 callgsubr
            return
          
    </CharString>
    
          
    <CharString index="45">
        
            -69 callsubr
            rlineto
            return
          
    </CharString>
    
          
    <CharString index="46">
        
            -230 53 199 -21 hstem
            176 66 vstem
            450 1 rmoveto
            -23 30 rlineto
            -179 -65 -72 -67 -58 vvcurveto
            -65 84 -43 157 82 vhcurveto
            -15 callsubr
            endchar
          
    </CharString>
    
          
    <CharString index="47">
        
            -12 66 -63 61 487 -20 23 -20 return
          
    </CharString>
    
          
    <CharString index="48">
        
            rmoveto
            -38 51 rlineto
            -298 -198 -120 -171 -184 vvcurveto
            -137 69 -148 167 -179 vhcurveto
            54 41 rlineto
            -157 163 -65 135 125 vvcurveto
            167 100 153 288 182 vhcurveto
            endchar
          
    </CharString>
    
          
    <CharString index="49">
        
            62 vstem
            189 472 -81 callsubr
            return
          
    </CharString>
    
          
    <CharString index="50">
        
            121 625 rlineto
            221 hlineto
            12 63 rlineto
            -515 hlineto
            -11 -63 rlineto
            220 hlineto
            -121 -625 rlineto
            return
          
    </CharString>
    
          
    <CharString index="51">
        
            631 14 callgsubr
            151 351 hintmask 01100000
            387 632 rmoveto
            71 2 44 146 rlineto
            hintmask 10100000
            -80 -2 rlineto
            -86 callsubr
            endchar
          
    </CharString>
    
          
    <CharString index="52">
        
            -93 -75 -186 -87 vvcurveto
            -68 59 -25 127 79 vhcurveto
            return
          
    </CharString>
    
          
    <CharString index="53">
        
            91 -123 103 -30 92 vhcurveto
            100 86 -9 64 -54 hhcurveto
            return
          
    </CharString>
    
          
    <CharString index="54">
        
            -11 62 -46 callsubr
            return
          
    </CharString>
    
          
    <CharString index="55">
        
            hintmask 01011000
            276 688 rmoveto
            -73 hlineto
            -134 -688 42 callsubr
            96 347 rmoveto
            hintmask 10011000
            219 -353 rlineto
            hintmask 00111000
            78 11 -214 341 328 342 rlineto
            -80 hlineto
            return
          
    </CharString>
    
          
    <CharString index="56">
        
            -12 59 446 59 -44 callgsubr
            return
          
    </CharString>
    
          
    <CharString index="57">
        
            hlineto
            -195 -137 rlineto
            hintmask 10010000
            -47 callsubr
            rlineto
            return
          
    </CharString>
    
          
    <CharString index="58">
        
            66 13 rlineto
            121 -17 -58 66 -111 hhcurveto
            return
          
    </CharString>
    
          
    <CharString index="59">
        
            -19 677 -486 -11 callgsubr
            return
          
    </CharString>
    
          
    <CharString index="60">
        
            32 -54 422 299 return
          
    </CharString>
    
          
    <CharString index="61">
        
            154 43 244 60 return
          
    </CharString>
    
          
    <CharString index="62">
        
            -174 -91 -92 4 -9 153 return
          
    </CharString>
    
          
    <CharString index="63">
        
            hstem
            82 68 335 68 vstem
            return
          
    </CharString>
    
          
    <CharString index="64">
        
            -30 callsubr
            hintmask 01010000
            -142 143 rlineto
            return
          
    </CharString>
    
          
    <CharString index="65">
        
            -16 65 639 -20 hstem
            91 73 vstem
            return
          
    </CharString>
    
          
    <CharString index="66">
        
            -11 66 434 60 return
          
    </CharString>
    
          
    <CharString index="67">
        
            rmoveto
            189 966 rlineto
            -341 hlineto
            -11 -57 rlineto
            272 hlineto
            -165 -851 rlineto
            -272 hlineto
            -12 -58 rlineto
            endchar
          
    </CharString>
    
          
    <CharString index="68">
        
            rmoveto
            28 -15 rlineto
            return
          
    </CharString>
    
          
    <CharString index="69">
        
            23 callsubr
            -64 -12 callsubr
            -206 hlineto
            -12 -60 rlineto
            207 -12 callsubr
            64 hlineto
            return
          
    </CharString>
    
          
    <CharString index="70">
        
            15 -21 27 7 callgsubr
            627 62 hstemhm
            return
          
    </CharString>
    
          
    <CharString index="71">
        
            hintmask 1000010001001000111110001000100001010110
            return
          
    </CharString>
    
          
    <CharString index="72">
        
            -131 -162 -138 -159 -239 vhcurveto
            46 9 rmoveto
            200 112 147 134 108 81 return
          
    </CharString>
    
          
    <CharString index="73">
        
            632 147 hstem
            259 116 vstem
            259 631 -66 callgsubr
            endchar
          
    </CharString>
    
          
    <CharString index="74">
        
            rmoveto
            215 -254 52 48 -204 237 310 236 -40 54 -314 -247 rlineto
            endchar
          
    </CharString>
    
          
    <CharString index="75">
        
            -8 64 583 62 hstem
            151 73 216 73 vstem
            return
          
    </CharString>
    
          
    <CharString index="76">
        
            60 188 59 return
          
    </CharString>
    
          
    <CharString index="77">
        
            hlineto
            178 125 rlineto
            hintmask 10010000
            -62 callsubr
            return
          
    </CharString>
    
          
    <CharString index="78">
        
            -244 47 219 -21 163 50 return
          
    </CharString>
    
          
    <CharString index="79">
        
            -189 63 150 65 403 59 return
          
    </CharString>
    
          
    <CharString index="80">
        
            663 -106 callgsubr
            return
          
    </CharString>
    
          
    <CharString index="81">
        
            rmoveto
            40 -53 314 246 19 74 -215 255 -52 -48 204 -238 rlineto
            endchar
          
    </CharString>
    
          
    <CharString index="82">
        
            -14 65 587 65 hstem
            84 72 352 69 vstem
            return
          
    </CharString>
    
          
    <CharString index="83">
        
            -19 677 -366 61 hstemhm
            return
          
    </CharString>
    
          
    <CharString index="84">
        
            hhcurveto
            71 13 -77 -108 -96 hvcurveto
            29 -18 rlineto
            148 149 -26 127 -116 hhcurveto
            return
          
    </CharString>
    
          
    <CharString index="85">
        
            rmoveto
            -10 36 -111 -46 -8 23 17 89 rlinecurve
            126 639 -71 -6 -45 -232 rlineto
            return
          
    </CharString>
    
          
    <CharString index="86">
        
            12 60 rlineto
            return
          
    </CharString>
    
          
    <CharString index="87">
        
            51 338 54 hstem
            return
          
    </CharString>
    
          
    <CharString index="88">
        
            318 41 callgsubr
            rlineto
            hintmask 00110000
            -253 -179 rlineto
            return
          
    </CharString>
    
          
    <CharString index="89">
        
            -6 34 31 -3 28 hhcurveto
            189 134 183 199 120 -54 61 -69 return
          
    </CharString>
    
          
    <CharString index="90">
        
            -63 callsubr
            endchar
          
    </CharString>
    
          
    <CharString index="91">
        
            rmoveto
            217 -141 88 -248 -43 vhcurveto
            return
          
    </CharString>
    
          
    <CharString index="92">
        
            -10 34 rlineto
            -118 -46 -47 21 37 vvcurveto
            40 61 48 147 52 vhcurveto
            return
          
    </CharString>
    
          
    <CharString index="93">
        
            hstem
            91 70 325 64 vstem
            return
          
    </CharString>
    
          
    <CharString index="94">
        
            -65 -2 -191 -979 rlineto
            return
          
    </CharString>
    
          
    <CharString index="95">
        
            hlineto
            -42 -213 rlineto
            return
          
    </CharString>
    
          
    <CharString index="96">
        
            -43 158 82 vhcurveto
            return
          
    </CharString>
    
          
    <CharString index="97">
        
            -11 66 437 59 -9 -20 258 -20 hstemhm
            68 69 257 66 return
          
    </CharString>
    
          
    <CharString index="98">
        
            -35 -29 29 35 35 29 29 35 hvcurveto
            return
          
    </CharString>
    
          
    <CharString index="99">
        
            45 141 46 return
          
    </CharString>
    
          
    <CharString index="100">
        
            hlineto
            12 59 rlineto
            return
          
    </CharString>
    
          
    <CharString index="101">
        
            hhcurveto
            47 37 -42 -89 -158 -94 -149 -123 hvcurveto
            endchar
          
    </CharString>
    
          
    <CharString index="102">
        
            -75 -93 -96 rlinecurve
            endchar
          
    </CharString>
    
          
    <CharString index="103">
        
            -237 53 189 -21 171 50 109 48 110 return
          
    </CharString>
    
          
    <CharString index="104">
        
            4 2 2 4 1 hvcurveto
            5 hlineto
            -6 -1 -4 -5 -8 hhcurveto
            return
          
    </CharString>
    
          
    <CharString index="105">
        
            53 182 -20 176 50 hstem
            return
          
    </CharString>
    
          
    <CharString index="106">
        
            -12 62 432 55 157 -20 return
          
    </CharString>
    
          
    <CharString index="107">
        
            96 hlineto
            25 117 rlineto
            -96 hlineto
            return
          
    </CharString>
    
          
    <CharString index="108">
        
            hintmask 1000010001001000111110001010000001010110
            return
          
    </CharString>
    
          
    <CharString index="109">
        
            hintmask 1100010001001000111110001000101000010110
            return
          
    </CharString>
    
          
    <CharString index="110">
        
            hstemhm
            89 71 264 60 return
          
    </CharString>
    
          
    <CharString index="111">
        
            58 241 58 vstem
            return
          
    </CharString>
    
          
    <CharString index="112">
        
            0 63 625 -20 return
          
    </CharString>
    
          
    <CharString index="113">
        
            56 213 54 return
          
    </CharString>
    
          
    <CharString index="114">
        
            15 -21 27 7 callgsubr
            480 65 229 -20 hstemhm
            return
          
    </CharString>
    
          
    <CharString index="115">
        
            178 -18 11 56 -177 19 36 181 -68 7 return
          
    </CharString>
    
          
    <CharString index="116">
        
            -51 hhcurveto
            endchar
          
    </CharString>
    
          
    <CharString index="117">
        
            46 hlineto
            27 122 66 246 31 129 rrcurveto
            return
          
    </CharString>
    
          
    <CharString index="118">
        
            0 62 150 55 55 54 251 61 hstem
            -10 return
          
    </CharString>
    
          
    <CharString index="119">
        
            -8 callgsubr
            306 67 return
          
    </CharString>
    
          
    <CharString index="120">
        
            rmoveto
            10 60 rlineto
            -435 hlineto
            -11 -60 rlineto
            endchar
          
    </CharString>
    
          
    <CharString index="121">
        
            35 callgsubr
            hstem
            return
          
    </CharString>
    
          
    <CharString index="122">
        
            47 186 42 return
          
    </CharString>
    
          
    <CharString index="123">
        
            117 58 return
          
    </CharString>
    
          
    <CharString index="124">
        
            17 85 rlinecurve
            return
          
    </CharString>
    
          
    <CharString index="125">
        
            rmoveto
            -23 -115 rlineto
            105 hlineto
            26 115 rlineto
            return
          
    </CharString>
    
          
    <CharString index="126">
        
            -11 61 440 61 return
          
    </CharString>
    
          
    <CharString index="127">
        
            41 186 47 hstem
            return
          
    </CharString>
    
          
    <CharString index="128">
        
            6 callsubr
            vstem
            return
          
    </CharString>
    
          
    <CharString index="129">
        
            -260 263 rlineto
            return
          
    </CharString>
    
          
    <CharString index="130">
        
            hlineto
            42 213 rlineto
            return
          
    </CharString>
    
          
    <CharString index="131">
        
            rlineto
            -117 return
          
    </CharString>
    
          
    <CharString index="132">
        
            hintmask 01100000
            43 callsubr
            return
          
    </CharString>
    
          
    <CharString index="133">
        
            64 -34 40 -62 -37 -36 -16 -28 -31 vhcurveto
            return
          
    </CharString>
    
          
    <CharString index="134">
        
            38 22 26 41 47 vvcurveto
            71 -57 57 -71 return
          
    </CharString>
    
          
    <CharString index="135">
        
            -75 85 -114 -176 -133 -220 return
          
    </CharString>
    
          
    <CharString index="136">
        
            15 7 callgsubr
            26 -21 683 -20 hstemhm
            return
          
    </CharString>
    
          
    <CharString index="137">
        
            hintmask 1000010001001000111101001000100001010110
            return
          
    </CharString>
    
          
    <CharString index="138">
        
            hintmask 1000010100001000111110001000100001010110
            return
          
    </CharString>
    
          
    <CharString index="139">
        
            hintmask 1000010001000100111110001001100001010110
            return
          
    </CharString>
    
          
    <CharString index="140">
        
            21 -21 625 63 hstem
            return
          
    </CharString>
    
          
    <CharString index="141">
        
            -23 -109 rlineto
            103 hlineto
            return
          
    </CharString>
    
          
    <CharString index="142">
        
            hstemhm
            390 73 2 75 return
          
    </CharString>
    
          
    <CharString index="143">
        
            hlineto
            -10 -56 rlineto
            return
          
    </CharString>
    
          
    <CharString index="144">
        
            rlineto
            -170 return
          
    </CharString>
    
          
    <CharString index="145">
        
            91 vvcurveto
            95 -62 52 -143 -20 vhcurveto
            return
          
    </CharString>
    
          
    <CharString index="146">
        
            6 -1 3 -4 -3 -2 -2 -7 vhcurveto
            return
          
    </CharString>
    
          
    <CharString index="147">
        
            -71 -57 -57 -71 -47 26 -41 38 -22 return
          
    </CharString>
    
          
    <CharString index="148">
        
            hlineto
            -11 -56 rlineto
            endchar
          
    </CharString>
    
          
    <CharString index="149">
        
            rlineto
            73 hlineto
            return
          
    </CharString>
    
          
    <CharString index="150">
        
            472 292 rmoveto
            12 61 rlineto
            return
          
    </CharString>
    
          
    <CharString index="151">
        
            -56 27 -685 -974 63 -17 return
          
    </CharString>
    
          
    <CharString index="152">
        
            -132 -188 rlineto
            return
          
    </CharString>
    
          
    <CharString index="153">
        
            hlineto
            -12 -61 rlineto
            return
          
    </CharString>
    
        
</Subrs>